agilkia/__init__.py
agilkia/data_generator.py
agilkia/json_traces.py
agilkia/random_tester.py
agilkia/trace_set_optimizer.py
agilkia-0.8.0.dist-info/LICENSE.txt
agilkia-0.8.0.dist-info/WHEEL
agilkia-0.8.0.dist-info/METADATA
agilkia-0.8.0.dist-info/RECORD
