Metadata-Version: 2.1
Name: agilkia
Version: 0.8.0
Summary: Automated smart testing strategies for web services.
Home-page: https://github.com/utting/agilkia
Keywords: automated testing, smart testing, machine learning test models, Philae
Author: Mark Utting
Author-email: m.utting@uq.edu.au
Requires-Python: >=3.7
Classifier: License :: OSI Approved :: MIT License
Classifier: Development Status :: 3 - Alpha
Classifier: Intended Audience :: Developers
Classifier: Natural Language :: English
Classifier: Operating System :: OS Independent
Classifier: Programming Language :: Python :: 3.8
Classifier: Topic :: Software Development :: Testing
Requires-Dist: flit>=3.0
Requires-Dist: ipython>=7.13.0
Requires-Dist: jsonpickle>=1.3
Requires-Dist: matplotlib>=3.2
Requires-Dist: pandas>=1.0.3
Requires-Dist: pillow>=7.0
Requires-Dist: pip>=20.0
Requires-Dist: requests>=2.23
Requires-Dist: scikit-learn>=0.22
Requires-Dist: scipy>=1.4.1
Requires-Dist: zeep>=3.4
Requires-Dist: pytest >=6.2.0 ; extra == "test"
Requires-Dist: pytest-cov>=2.11 ; extra == "test"
Requires-Dist: mypy>=0.740 ; extra == "test"
Provides-Extra: test
